{
    "192.168.1.124": {
        "ports": {},
        "services": {},
        "vulns": []
    },
    "192.168.1.199": {
        "ports": {},
        "services": {},
        "vulns": []
    },
    "192.168.1.90": {
        "ports": {},
        "services": {},
        "vulns": []
    },
    "192.168.1.114": {
        "ports": {
            "80": "open",
            "443": "open",
            "631": "open",
            "8080": "open",
            "9100": "open"
        },
        "services": {
            "80": "http HP DeskJet 2700 series printer http config (Serial CN1636A1ZG)",
            "443": "ssl/http HP DeskJet 2700 series printer http config (Serial CN1636A1ZG)",
            "631": "http HP DeskJet 2700 series printer http config (Serial CN1636A1ZG)",
            "8080": "http HP DeskJet 2700 series printer http config (Serial CN1636A1ZG)",
            "9100": "jetdirect ?"
        },
        "vulns": [
            {
                "port": 80,
                "issue": "HTTP non chiffré",
                "severity": "medium"
            },
            {
                "port": 80,
                "issue": "HTTP non chiffré",
                "severity": "medium"
            },
            {
                "port": 631,
                "issue": "HTTP non chiffré",
                "severity": "medium"
            },
            {
                "port": 8080,
                "issue": "HTTP non chiffré",
                "severity": "medium"
            }
        ]
    },
    "192.168.1.88": {
        "ports": {
            "49152": "open"
        },
        "services": {
            "49152": "tcpwrapped"
        },
        "vulns": []
    },
    "192.168.1.60": {
        "ports": {
            "8008": "open",
            "8009": "open",
            "8443": "open"
        },
        "services": {},
        "vulns": []
    },
    "192.168.1.32": {
        "ports": {
            "443": "open",
            "554": "open"
        },
        "services": {},
        "vulns": []
    },
    "192.168.1.231": {
        "ports": {
            "8888": "open"
        },
        "services": {
            "8888": "sun-answerbook ?"
        },
        "vulns": []
    },
    "192.168.1.38": {
        "ports": {},
        "services": {},
        "vulns": []
    }
}